{
  "lastUpdated": "2026-04-12T13:06:39.050Z",
  "channelCount": 12,
  "videoCount": 1,
  "archiveCount": 1,
  "taggedCount": 33,
  "latest": [
    {
      "id": "aHR0cHM6Ly93d3cueW91dHVi",
      "videoId": "45gmsSZh_yQ",
      "show": "Shawn Ryan Show",
      "title": "This Was Going So Well… 😂",
      "url": "https://www.youtube.com/watch?v=45gmsSZh_yQ",
      "date": "2026-04-12T00:00:06.000Z",
      "image": "https://i1.ytimg.com/vi/45gmsSZh_yQ/hqdefault.jpg",
      "desc": "Join this channel to get access to perks:\nhttps://www.youtube.com/channel/UCkoujZQZatbqy4KGcgjpVxQ/join\n\nSupport the Shawn Ryan Show for $5 and get the chance to watch the shows AD FREE, with the exception of Shawn's personal reads, before they release!! Sign up here: https://www.patreon.com/Vigilan",
      "guestTags": []
    }
  ],
  "archive": [
    {
      "id": "aHR0cHM6Ly93d3cueW91dHVi",
      "videoId": "45gmsSZh_yQ",
      "show": "Shawn Ryan Show",
      "title": "This Was Going So Well… 😂",
      "url": "https://www.youtube.com/watch?v=45gmsSZh_yQ",
      "date": "2026-04-12T00:00:06.000Z",
      "image": "https://i1.ytimg.com/vi/45gmsSZh_yQ/hqdefault.jpg",
      "desc": "Join this channel to get access to perks:\nhttps://www.youtube.com/channel/UCkoujZQZatbqy4KGcgjpVxQ/join\n\nSupport the Shawn Ryan Show for $5 and get the chance to watch the shows AD FREE, with the exception of Shawn's personal reads, before they release!! Sign up here: https://www.patreon.com/Vigilan",
      "guestTags": []
    }
  ],
  "guestIndex": {}
}