{
  "lastUpdated": "2026-04-03T05:52:57.287Z",
  "channelCount": 12,
  "videoCount": 1,
  "archiveCount": 1,
  "taggedCount": 0,
  "latest": [
    {
      "id": "aHR0cHM6Ly93d3cueW91dHVi",
      "videoId": "rp84hT_pw3o",
      "show": "Shawn Ryan Show",
      "title": "They Found 3D Data on the Shroud of Turin 😳",
      "url": "https://www.youtube.com/watch?v=rp84hT_pw3o",
      "date": "2026-04-03T00:01:00.000Z",
      "image": "https://i3.ytimg.com/vi/rp84hT_pw3o/hqdefault.jpg",
      "desc": "Join this channel to get access to perks:\nhttps://www.youtube.com/channel/UCkoujZQZatbqy4KGcgjpVxQ/join\n\nSupport the Shawn Ryan Show for $5 and get the chance to watch the shows AD FREE, with the exception of Shawn's personal reads, before they release!! Sign up here: https://www.patreon.com/Vigilan",
      "guestTags": []
    }
  ],
  "archive": [
    {
      "id": "aHR0cHM6Ly93d3cueW91dHVi",
      "videoId": "rp84hT_pw3o",
      "show": "Shawn Ryan Show",
      "title": "They Found 3D Data on the Shroud of Turin 😳",
      "url": "https://www.youtube.com/watch?v=rp84hT_pw3o",
      "date": "2026-04-03T00:01:00.000Z",
      "image": "https://i3.ytimg.com/vi/rp84hT_pw3o/hqdefault.jpg",
      "desc": "Join this channel to get access to perks:\nhttps://www.youtube.com/channel/UCkoujZQZatbqy4KGcgjpVxQ/join\n\nSupport the Shawn Ryan Show for $5 and get the chance to watch the shows AD FREE, with the exception of Shawn's personal reads, before they release!! Sign up here: https://www.patreon.com/Vigilan",
      "guestTags": []
    }
  ],
  "guestIndex": {}
}